simple_parsing/__init__.py
simple_parsing/_version.py
simple_parsing/conflicts.py
simple_parsing/decorators.py
simple_parsing/docstring.py
simple_parsing/help_formatter.py
simple_parsing/parsing.py
simple_parsing/py.typed
simple_parsing/replace.py
simple_parsing/utils.py
simple_parsing/annotation_utils/__init__.py
simple_parsing/annotation_utils/get_field_annotations.py
simple_parsing/helpers/__init__.py
simple_parsing/helpers/custom_actions.py
simple_parsing/helpers/fields.py
simple_parsing/helpers/flatten.py
simple_parsing/helpers/nested_partial.py
simple_parsing/helpers/partial.py
simple_parsing/helpers/subgroups.py
simple_parsing/helpers/hparams/__init__.py
simple_parsing/helpers/hparams/hparam.py
simple_parsing/helpers/hparams/hyperparameters.py
simple_parsing/helpers/hparams/hyperparameters_test.py
simple_parsing/helpers/hparams/priors.py
simple_parsing/helpers/hparams/priors_test.py
simple_parsing/helpers/hparams/utils.py
simple_parsing/helpers/serialization/__init__.py
simple_parsing/helpers/serialization/decoding.py
simple_parsing/helpers/serialization/encoding.py
simple_parsing/helpers/serialization/serializable.py
simple_parsing/helpers/serialization/yaml_serialization.py
simple_parsing/wrappers/__init__.py
simple_parsing/wrappers/dataclass_wrapper.py
simple_parsing/wrappers/field_metavar.py
simple_parsing/wrappers/field_parsing.py
simple_parsing/wrappers/field_wrapper.py
simple_parsing/wrappers/wrapper.py
simple_parsing-0.1.5.dist-info/LICENSE
simple_parsing-0.1.5.dist-info/METADATA
simple_parsing-0.1.5.dist-info/WHEEL
simple_parsing-0.1.5.dist-info/top_level.txt
simple_parsing-0.1.5.dist-info/RECORD
