Metadata-Version: 2.1
Name: simple_parsing
Version: 0.1.5
Summary: A small utility for simplifying and cleaning up argument parsing scripts.
Home-page: https://github.com/lebrice/SimpleParsing
Author: Fabrice Normandin
Author-email: fabrice.normandin@gmail.com
Classifier: Programming Language :: Python :: 3
Classifier: License :: OSI Approved :: MIT License
Classifier: Operating System :: OS Independent
Requires-Python: >=3.7
License-File: LICENSE
Requires-Dist: docstring-parser~=0.15
Requires-Dist: typing_extensions>=4.5.0
Provides-Extra: test
Requires-Dist: pytest; extra == "test"
Requires-Dist: pytest-xdist; extra == "test"
Requires-Dist: pytest-regressions; extra == "test"
Requires-Dist: pytest-benchmark; extra == "test"
Requires-Dist: numpy; extra == "test"
Provides-Extra: yaml
Requires-Dist: pyyaml; extra == "yaml"
Provides-Extra: toml
Requires-Dist: tomli; extra == "toml"
Requires-Dist: tomli_w; extra == "toml"
Provides-Extra: all
Requires-Dist: pytest; extra == "all"
Requires-Dist: pytest-regressions; extra == "all"
Requires-Dist: pyyaml; extra == "all"
Requires-Dist: pytest-benchmark; extra == "all"
Requires-Dist: numpy; extra == "all"
Requires-Dist: tomli_w; extra == "all"
Requires-Dist: pytest-xdist; extra == "all"
Requires-Dist: tomli; extra == "all"
